skyvault/__init__.py
skyvault/aes.py
skyvault/ini_operations.py
skyvault-2.0.1.dist-info/LICENSE
skyvault-2.0.1.dist-info/METADATA
skyvault-2.0.1.dist-info/WHEEL
skyvault-2.0.1.dist-info/top_level.txt
skyvault-2.0.1.dist-info/RECORD
